_cubao_pybind.cpython-38-darwin.so
cubao_pybind-0.0.3.dist-info/RECORD
cubao_pybind-0.0.3.dist-info/LICENSE
cubao_pybind-0.0.3.dist-info/WHEEL
cubao_pybind-0.0.3.dist-info/top_level.txt
cubao_pybind-0.0.3.dist-info/METADATA
cubao_pybind/__init__.py
cubao_pybind/__main__.py
