Metadata-Version: 2.1
Name: cubao-pybind
Version: 0.0.3
Summary: misc c++ code in cubao
Home-page: https://cubao-pybind.readthedocs.io
Author: tzx
Author-email: dvorak4tzx@gmail.com
Requires-Python: >=3.7
License-File: LICENSE
Requires-Dist: fire
Requires-Dist: loguru
Requires-Dist: tqdm
Provides-Extra: test
Requires-Dist: pytest>=6.0; extra == "test"
